{
  "artist": "Eagles",
  "title": "Hotel California",
  "key": "Am",
  "sections": [
    {
      "name": "Intro",
      "lines": [
        {
          "chord": null,
          "lyric": "Tabbed by: Emrldeyzs"
        },
        {
          "chord": null,
          "lyric": "Capo 2"
        },
        {
          "chord": null,
          "lyric": "x2"
        }
      ]
    },
    {
      "name": "Verse",
      "lines": [
        {
          "chord": {
            "name": "Am"
          },
          "lyric": "On a dark desert highway,"
        },
        {
          "chord": {
            "name": "E7"
          },
          "lyric": "cool wind in my hair"
        },
        {
          "chord": {
            "name": "G"
          },
          "lyric": "Warm smell of colitas"
        },
        {
          "chord": {
            "name": "D"
          },
          "lyric": "rising up through the air"
        },
        {
          "chord": {
            "name": "F"
          },
          "lyric": "Up ahead in the distance,"
        },
        {
          "chord": {
            "name": "C"
          },
          "lyric": "I saw a shimmering light"
        },
        {
          "chord": {
            "name": "Dm"
          },
          "lyric": "My head grew heavy and my sight grew dim"
        },
        {
          "chord": {
            "name": "E7"
          },
          "lyric": "I had to stop for the night"
        },
        {
          "chord": {
            "name": "Am"
          },
          "lyric": "There she stood in the doorway;"
        },
        {
          "chord": {
            "name": "E7"
          },
          "lyric": "I heard the mission bell"
        },
        {
          "chord": {
            "name": "G"
          },
          "lyric": "And I was thinking to myself"
        },
        {
          "chord": {
            "name": "D"
          },
          "lyric": "heaven or this could be hell"
        },
        {
          "chord": {
            "name": "F"
          },
          "lyric": "Then she lit up a candle,"
        },
        {
          "chord": {
            "name": "C"
          },
          "lyric": "and she showed me the way"
        },
        {
          "chord": {
            "name": "Dm"
          },
          "lyric": "There were voices down the corridor,"
        },
        {
          "chord": {
            "name": "E7"
          },
          "lyric": "I thought I heard them say..."
        }
      ]
    },
    {
      "name": "Chorus",
      "lines": [
        {
          "chord": {
            "name": "F"
          },
          "lyric": "Welcome to the Hotel Cali"
        },
        {
          "chord": {
            "name": "C"
          },
          "lyric": "fornia."
        },
        {
          "chord": {
            "name": "E7"
          },
          "lyric": "lovely place (such a lovely place), such a"
        },
        {
          "chord": {
            "name": "Am"
          },
          "lyric": "lovely face"
        },
        {
          "chord": {
            "name": "F"
          },
          "lyric": "Plenty of room at the Hotel Cali"
        },
        {
          "chord": {
            "name": "C"
          },
          "lyric": "fornia"
        },
        {
          "chord": {
            "name": "Dm"
          },
          "lyric": "time of year (any time of year), you can"
        },
        {
          "chord": {
            "name": "E7"
          },
          "lyric": "find it here"
        }
      ]
    },
    {
      "name": "Verse",
      "lines": [
        {
          "chord": {
            "name": "Am"
          },
          "lyric": "Her mind is Tiffany-twisted,"
        },
        {
          "chord": {
            "name": "E7"
          },
          "lyric": "she got the Mercedes bends"
        },
        {
          "chord": {
            "name": "G"
          },
          "lyric": "She got a lot of pretty pretty boys"
        },
        {
          "chord": {
            "name": "D"
          },
          "lyric": "she calls friends"
        },
        {
          "chord": {
            "name": "F"
          },
          "lyric": "How they danced in the courtyard,"
        },
        {
          "chord": {
            "name": "C"
          },
          "lyric": "sweet summer sweat"
        },
        {
          "chord": {
            "name": "Dm"
          },
          "lyric": "Some dance to remember,"
        },
        {
          "chord": {
            "name": "E7"
          },
          "lyric": "some dance to forget"
        },
        {
          "chord": {
            "name": "Am"
          },
          "lyric": "So I called up the captain;"
        },
        {
          "chord": {
            "name": "E7"
          },
          "lyric": "Please bring me my wine (he said)"
        },
        {
          "chord": {
            "name": "G"
          },
          "lyric": "We haven't had that spirit here since"
        },
        {
          "chord": {
            "name": "D"
          },
          "lyric": "1969"
        },
        {
          "chord": {
            "name": "F"
          },
          "lyric": "and still those voices are calling from"
        },
        {
          "chord": {
            "name": "C"
          },
          "lyric": "far away"
        },
        {
          "chord": {
            "name": "Dm"
          },
          "lyric": "Wake you up in the middle of the night"
        },
        {
          "chord": {
            "name": "E7"
          },
          "lyric": "Just to hear them say..."
        }
      ]
    },
    {
      "name": "Chorus",
      "lines": [
        {
          "chord": {
            "name": "F"
          },
          "lyric": "Welcome to the Hotel Cali"
        },
        {
          "chord": {
            "name": "C"
          },
          "lyric": "fornia."
        },
        {
          "chord": {
            "name": "E7"
          },
          "lyric": "lovely place (such a lovely place), such a"
        },
        {
          "chord": {
            "name": "Am"
          },
          "lyric": "lovely face"
        },
        {
          "chord": {
            "name": "F"
          },
          "lyric": "livin' it up at the Hotel Cali"
        },
        {
          "chord": {
            "name": "C"
          },
          "lyric": "fornia"
        },
        {
          "chord": {
            "name": "Dm"
          },
          "lyric": "nice surprise (what a nice surprise), bring your"
        },
        {
          "chord": {
            "name": "E7"
          },
          "lyric": "alibis"
        }
      ]
    },
    {
      "name": "Verse",
      "lines": [
        {
          "chord": {
            "name": "Am"
          },
          "lyric": "Mirrors on the ceiling;"
        },
        {
          "chord": {
            "name": "E7"
          },
          "lyric": "the pink champagne on ice (and she said)"
        },
        {
          "chord": {
            "name": "G"
          },
          "lyric": "We are all just prisoners here,"
        },
        {
          "chord": {
            "name": "D"
          },
          "lyric": "of our own device"
        },
        {
          "chord": {
            "name": "F"
          },
          "lyric": "and in the master's chambers,"
        },
        {
          "chord": {
            "name": "C"
          },
          "lyric": "they gathered for the feast"
        },
        {
          "chord": {
            "name": "Dm"
          },
          "lyric": "They stab it with their steely knives but they"
        },
        {
          "chord": {
            "name": "E7"
          },
          "lyric": "just can't kill the beast"
        },
        {
          "chord": {
            "name": "Am"
          },
          "lyric": "Last thing I remember, I was"
        },
        {
          "chord": {
            "name": "E7"
          },
          "lyric": "running for the door"
        },
        {
          "chord": {
            "name": "G"
          },
          "lyric": "I had to find the passage back to the"
        },
        {
          "chord": {
            "name": "D"
          },
          "lyric": "place I was before"
        },
        {
          "chord": {
            "name": "F"
          },
          "lyric": "\"Relax\" said the night man; we are"
        },
        {
          "chord": {
            "name": "C"
          },
          "lyric": "programmed to receive"
        },
        {
          "chord": {
            "name": "Dm"
          },
          "lyric": "You can check out any time you like"
        },
        {
          "chord": {
            "name": "E7"
          },
          "lyric": "But you can never leave..."
        }
      ]
    },
    {
      "name": "Outro Solo",
      "lines": [
        {
          "chord": null,
          "lyric": "x3"
        }
      ]
    },
    {
      "name": "Harmonies",
      "lines": [
        {
          "chord": {
            "name": "Am"
          },
          "lyric": "(fade"
        },
        {
          "chord": {
            "name": "E7"
          },
          "lyric": "out)"
        },
        {
          "chord": {
            "name": "G"
          },
          "lyric": ""
        },
        {
          "chord": {
            "name": "D"
          },
          "lyric": ""
        },
        {
          "chord": {
            "name": "F"
          },
          "lyric": ""
        },
        {
          "chord": {
            "name": "C"
          },
          "lyric": ""
        },
        {
          "chord": {
            "name": "Dm"
          },
          "lyric": ""
        },
        {
          "chord": {
            "name": "E7"
          },
          "lyric": ""
        }
      ]
    }
  ]
}